DitchCarbon/__init__.py
DitchCarbon/ditchcarbon.py
ditchcarbon-0.1.1.dist-info/METADATA
ditchcarbon-0.1.1.dist-info/WHEEL
ditchcarbon-0.1.1.dist-info/licenses/LICENSE
ditchcarbon-0.1.1.dist-info/RECORD
