Metadata-Version: 2.1
Name: DitchCarbon
Version: 0.1.1
Summary: Introducing "DitchCarbon", an open-source Python package that allows users to easily call the DitchCarbon API using HTTP requests.
Author-email: Luke Cummins <lc2232@bath.ac.uk>, Alex Dawkins <asd60@bath.ac.uk>, Joe Downard <jhd35@bath.ac.uk>, Sergios Gavriilidis <sg2295@bath.ac.uk>
License-File: LICENSE
Classifier: License :: OSI Approved
Classifier: Operating System :: OS Independent
Classifier: Programming Language :: Python :: 3
Requires-Python: >=3.9
Requires-Dist: requests
